wordin2D/__init__.py
wordsin2D-0.0.1.dist-info/LICENSE.txt
wordsin2D-0.0.1.dist-info/METADATA
wordsin2D-0.0.1.dist-info/WHEEL
wordsin2D-0.0.1.dist-info/top_level.txt
wordsin2D-0.0.1.dist-info/RECORD
